redilock/__init__.py
redilock/async_redilock.py
redilock/base.py
redilock/sync_redilock.py
python_redilock-0.5.0.dist-info/LICENSE
python_redilock-0.5.0.dist-info/METADATA
python_redilock-0.5.0.dist-info/WHEEL
python_redilock-0.5.0.dist-info/top_level.txt
python_redilock-0.5.0.dist-info/RECORD
