Metadata-Version: 2.1
Name: python-redilock
Version: 0.5.0
Summary: Redis Distributed Lock
Author-email: Zvika Ferentz <zvika.ferentz@gmail.com>
License: MIT License
Project-URL: Homepage, https://github.com/zferentz/python-redilock
Project-URL: Issues, https://github.com/zferentz/python-redilock/issues
Keywords: redis,lock,mutex,distributed
Classifier: Programming Language :: Python :: 3.10
Classifier: License :: OSI Approved :: MIT License
Classifier: Operating System :: OS Independent
Requires-Python: >=3.10
License-File: LICENSE
Requires-Dist: redis >=4.3.1
